README.rst
dynamic.py
setup.py
dynamic.egg-info/PKG-INFO
dynamic.egg-info/SOURCES.txt
dynamic.egg-info/dependency_links.txt
dynamic.egg-info/top_level.txt