Metadata-Version: 1.1
Name: dynamic
Version: 0.1
Summary: Class to create dynamic objects.
Home-page: https://github.com/gravmatt/py-dynamic
Author: Rene Tanczos
Author-email: gravmatt@gmail.com
License: MIT
Platform: MacOSX
Platform: UNIX/Linux
Classifier: Intended Audience :: Developers
Classifier: License :: OSI Approved :: MIT License
Classifier: Programming Language :: Python :: 2.5
Classifier: Programming Language :: Python :: 2.6
Classifier: Programming Language :: Python :: 2.7
Classifier: Programming Language :: Python :: 3
Classifier: Programming Language :: Python :: 3.2
Classifier: Programming Language :: Python :: 3.3
Classifier: Intended Audience :: Developers
Classifier: Programming Language :: Python
Classifier: Development Status :: 5 - Production/Stable
